CHANGES.rst
CREDITS.rst
LICENSE.rst
MANIFEST.in
README.rst
setup.cfg
setup.py
githubinfo/__init__.py
githubinfo/commits.py
githubinfo/tests.py
githubinfo/testsettings.json
githubinfo.egg-info/PKG-INFO
githubinfo.egg-info/SOURCES.txt
githubinfo.egg-info/dependency_links.txt
githubinfo.egg-info/entry_points.txt
githubinfo.egg-info/not-zip-safe
githubinfo.egg-info/requires.txt
githubinfo.egg-info/top_level.txt