Metadata-Version: 1.0
Name: githubinfo
Version: 1.0
Summary: Extract test-related commit info from github
Home-page: https://github.com/nens/githubinfo
Author: Reinout van Rees
Author-email: reinout@vanrees.org
License: GPL
Platform: UNKNOWN
